water_cli/__init__.py
water_cli/exceptions.py
water_cli/parser.py
water_cli/utils.py
water_cli-0.1.16.dist-info/METADATA
water_cli-0.1.16.dist-info/WHEEL
water_cli-0.1.16.dist-info/RECORD
