Metadata-Version: 2.1
Name: water_cli
Version: 0.1.16
Summary: 
Home-page: https://github.com/DavidVentura/water
Author: david
Author-email: davidventura27@gmail.com
Requires-Python: >=3.7,<4.0
Classifier: Programming Language :: Python :: 3
Classifier: Programming Language :: Python :: 3.7
Classifier: Programming Language :: Python :: 3.8
Classifier: Programming Language :: Python :: 3.9
Classifier: Programming Language :: Python :: 3.10
Classifier: Programming Language :: Python :: 3.11
Requires-Dist: typing-extensions (>=4.0.0,<5.0.0) ; python_version < "3.10"
Project-URL: Repository, https://github.com/DavidVentura/water
